{
  "NTProvider": {
    "types": {
      "/AdvantageKit/RealOutputs/Alerts": "Alerts",
      "/FMSInfo": "FMSInfo",
      "/SmartDashboard/Alerts": "Alerts",
      "/SmartDashboard/Auto Chooser": "String Chooser",
      "/SmartDashboard/FF Rot Controller": "ProfiledPIDController",
      "/SmartDashboard/FF TRans": "ProfiledPIDController",
      "/SmartDashboard/Field": "Field2d",
      "/SmartDashboard/Intaking Chooser": "String Chooser",
      "/SmartDashboard/Level Chooser": "String Chooser",
      "/SmartDashboard/Repulsor Rot": "PIDController",
      "/SmartDashboard/Repulsor Trans": "PIDController",
      "/SmartDashboard/VisionSystemSim-main/Sim Field": "Field2d"
    }
  },
  "NetworkTables Info": {
    "visible": true
  }
}
